dhs_cli.py
dhsecrets/__init__.py
dhsecrets/dhsecrets.py
dhsecrets-0.0.3.dist-info/licenses/LICENSE
dhsecrets-0.0.3.dist-info/METADATA
dhsecrets-0.0.3.dist-info/WHEEL
dhsecrets-0.0.3.dist-info/entry_points.txt
dhsecrets-0.0.3.dist-info/top_level.txt
dhsecrets-0.0.3.dist-info/RECORD
