Metadata-Version: 2.4
Name: DHsecrets
Version: 0.0.3
Summary: Diffie-Hellman based secret secure exchange.
Home-page: https://github.com/valerio-vaccaro/DH-secrets
Author: Valerio Vaccaro
Author-email: valerio.vaccaro@gmail.com
License: MIT
Classifier: Programming Language :: Python :: 3.7
Classifier: Operating System :: OS Independent
Requires-Python: >=3.7
License-File: LICENSE
Requires-Dist: wallycore==1.5.1
Dynamic: author
Dynamic: author-email
Dynamic: classifier
Dynamic: description
Dynamic: description-content-type
Dynamic: home-page
Dynamic: license
Dynamic: license-file
Dynamic: requires-dist
Dynamic: requires-python
Dynamic: summary
